bi_sc_client/__init__.py
bi_sc_client/client.py
bi_sc_client/errors.py
bi_sc_client/resources/__init__.py
bi_sc_client/resources/token.py
bi_sc_client/services/__init__.py
bi_sc_client/services/invoice_pdf_regenerate.py
bi_sc_client/services/notify_invoice_number.py
bi_sc_client-0.0.5.dist-info/METADATA
bi_sc_client-0.0.5.dist-info/WHEEL
bi_sc_client-0.0.5.dist-info/top_level.txt
bi_sc_client-0.0.5.dist-info/RECORD
