Metadata-Version: 2.4
Name: bi-sc-client
Version: 0.0.5
Summary: Python wrapper for BI SomConnexió API
Home-page: https://git.coopdevs.org/coopdevs/som-connexio/bi/bi-sc-client
Author: Coopdevs, Som Connexio
Author-email: info@coopdevs.org
Maintainer: Daniel Palomar
Classifier: Development Status :: 3 - Alpha
Classifier: Operating System :: POSIX :: Linux
Classifier: Programming Language :: Python :: 3
Classifier: Programming Language :: Python :: 3.7
Requires-Dist: requests==2.28.1
Dynamic: author
Dynamic: author-email
Dynamic: classifier
Dynamic: description
Dynamic: description-content-type
Dynamic: home-page
Dynamic: maintainer
Dynamic: requires-dist
Dynamic: summary
